source/__init__.py
source/entities/__init__.py
source/entities/devcontainer_json.py
source/entities/enums.py
source/entities/exceptions.py
source/entities/settings_json.py
source/frameworks_and_devices/__init__.py
source/frameworks_and_devices/cli.py
source/interface_adapters/__init__.py
source/interface_adapters/controller.py
source/use_cases/__init__.py
vscode_project_cli-0.1.4.dist-info/LICENSE
vscode_project_cli-0.1.4.dist-info/METADATA
vscode_project_cli-0.1.4.dist-info/WHEEL
vscode_project_cli-0.1.4.dist-info/entry_points.txt
vscode_project_cli-0.1.4.dist-info/RECORD
